json_plist_mobileconfig/__init__.py
json_plist_mobileconfig/converter.py
json_plist_mobileconfig/tests/__init__.py
json_plist_mobileconfig/tests/conftest.py
json_plist_mobileconfig/tests/fixtures/test_data.json
json_plist_mobileconfig/tests/fixtures/test_data.plist
json_plist_mobileconfig/tests/test_cli.py
json_plist_mobileconfig/tests/test_library.py
json_plist_mobileconfig-0.1.0.dist-info/LICENSE
json_plist_mobileconfig-0.1.0.dist-info/METADATA
json_plist_mobileconfig-0.1.0.dist-info/WHEEL
json_plist_mobileconfig-0.1.0.dist-info/entry_points.txt
json_plist_mobileconfig-0.1.0.dist-info/RECORD
