Metadata-Version: 2.1
Name: json-plist-mobileconfig
Version: 0.1.0
Summary: A Python package to convert files between JSON, plist, and mobileconfig 'Custom Settings' formats.
License: MIT
Author: Robert Coleman
Author-email: pypi@robert.net.nz
Requires-Python: >=3.7,<4.0
Classifier: License :: OSI Approved :: MIT License
Classifier: Programming Language :: Python :: 3
Classifier: Programming Language :: Python :: 3.7
Classifier: Programming Language :: Python :: 3.8
Classifier: Programming Language :: Python :: 3.9
Classifier: Programming Language :: Python :: 3.10
Classifier: Programming Language :: Python :: 3.11
